posterum/__init__.py
posterum/main.py
posterum/common/__init__.py
posterum/common/cache.py
posterum/common/errors.py
posterum/common/smtp.py
posterum/controllers/__init__.py
posterum/controllers/address.py
posterum/controllers/base.py
posterum/controllers/root.py
posterum-0.1.1.dist-info/METADATA
posterum-0.1.1.dist-info/WHEEL
posterum-0.1.1.dist-info/top_level.txt
posterum-0.1.1.dist-info/RECORD
