Metadata-Version: 2.1
Name: posterum
Version: 0.1.1
Summary: Simple e-mail address SMTP verification service
Home-page: https://posterum.bemisc.com
Author: João Magalhães
Author-email: joamag@gmail.com
License: Apache License, Version 2.0
Keywords: post smtp validation
Classifier: Development Status :: 5 - Production/Stable
Classifier: Topic :: Utilities
Classifier: License :: OSI Approved :: Apache Software License
Classifier: Operating System :: OS Independent
Classifier: Programming Language :: Python
Classifier: Programming Language :: Python :: 3.10
Classifier: Programming Language :: Python :: 3.11
Classifier: Programming Language :: Python :: 3.12
Requires-Dist: appier
Requires-Dist: appier-extras
Requires-Dist: jinja2
Requires-Dist: fastapi
